lti_store/__init__.py
lti_store/admin.py
lti_store/apps.py
lti_store/models.py
lti_store/pipelines.py
lti_store/migrations/0001_initial.py
lti_store/migrations/0002_add_lti_1p3_fields.py
lti_store/migrations/0003_alter_externallticonfiguration_lti_1p1_client_key_and_more.py
lti_store/migrations/0003_alter_externallticonfiguration_lti_1p3_public_jwk.py
lti_store/migrations/__init__.py
openedx_ltistore-1.1.3.dist-info/licenses/LICENSE.txt
openedx_ltistore-1.1.3.dist-info/METADATA
openedx_ltistore-1.1.3.dist-info/WHEEL
openedx_ltistore-1.1.3.dist-info/entry_points.txt
openedx_ltistore-1.1.3.dist-info/top_level.txt
openedx_ltistore-1.1.3.dist-info/RECORD
