Metadata-Version: 2.4
Name: openedx-ltistore
Version: 1.1.3
Summary: An app for storing LTI provider configurations centrally.
Home-page: https://github.com/openedx/openedx-ltistore
Author: edX
Author-email: oscm@edx.org
License: AGPL 3.0
Keywords: Python edx
Classifier: Development Status :: 3 - Alpha
Classifier: Intended Audience :: Developers
Classifier: License :: OSI Approved :: GNU Affero General Public License v3 or later (AGPLv3+)
Classifier: Natural Language :: English
Classifier: Programming Language :: Python :: 3
Classifier: Programming Language :: Python :: 3.11
Classifier: Programming Language :: Python :: 3.12
Classifier: Framework :: Django
Classifier: Framework :: Django :: 4.2
Classifier: Framework :: Django :: 5.2
Requires-Python: >=3.11
License-File: LICENSE.txt
Requires-Dist: django
Requires-Dist: openedx-filters
Requires-Dist: pycryptodomex
Requires-Dist: pyjwkest
Dynamic: author
Dynamic: author-email
Dynamic: classifier
Dynamic: description
Dynamic: description-content-type
Dynamic: home-page
Dynamic: keywords
Dynamic: license
Dynamic: license-file
Dynamic: requires-dist
Dynamic: requires-python
Dynamic: summary
